ec_data_analysis/__init__.py
ec_data_analysis/battery.py
ec_data_analysis/constants.py
ec_data_analysis/ec_dataset.py
ec_data_analysis/market_solution.py
ec_data_analysis/plot_utils.py
ec_data_analysis/report.py
ec_data_analysis/report_texts/buyRatio.md
ec_data_analysis/report_texts/chargeRatio.md
ec_data_analysis/report_texts/dischargeRatio.md
ec_data_analysis/report_texts/energyBreakdown.md
ec_data_analysis/report_texts/energyBreakdownWithBattery.md
ec_data_analysis/report_texts/introduction.md
ec_data_analysis/report_texts/keyStats.md
ec_data_analysis/report_texts/sellRatio.md
ec_data_analysis/report_texts/statsWithBattery.md
ec_data_analysis/report_texts/supplyDemandCapacityCurves.md
ec_data_analysis/report_texts/unfairBuyRatio.md
ec_data_analysis/report_texts/unfairSellRatio.md
ec_data_analysis-0.9.1.dist-info/METADATA
ec_data_analysis-0.9.1.dist-info/WHEEL
ec_data_analysis-0.9.1.dist-info/RECORD
