Metadata-Version: 2.1
Name: ec-data-analysis
Version: 0.9.1
Summary: Manages Energy Community Datasets with support for computing optimal energy distribution, visualization and key statistics.
Home-page: https://github.com/skehrli/ec-data-analysis
License: MIT
Author: Sascha Kehrli
Author-email: skehrli@ethz.ch
Requires-Python: >=3.10,<4.0
Classifier: License :: OSI Approved :: MIT License
Classifier: Programming Language :: Python :: 3
Classifier: Programming Language :: Python :: 3.10
Classifier: Programming Language :: Python :: 3.11
Classifier: Programming Language :: Python :: 3.12
Requires-Dist: markdown-pdf (>=1.3,<2.0)
Requires-Dist: matplotlib (>=3.9.2,<4.0.0)
Requires-Dist: networkx (>=3.3,<4.0)
Requires-Dist: numpy (>=2.1.1,<3.0.0)
Requires-Dist: openpyxl (>=3.1.5,<4.0.0)
Requires-Dist: pandas (>=2.2.2,<3.0.0)
Requires-Dist: seaborn (>=0.13.2,<0.14.0)
Project-URL: Repository, https://github.com/skehrli/ec-data-analysis
